chromepy/__init__.py
chromepy/chrome.py
chromepy/common.py
chromepy/remote.py
chromepy/screenshot.py
examples/__init__.py
examples/start_chrome.py
examples/start_remote.py
ChromePy-0.0.4.dist-info/LICENSE
ChromePy-0.0.4.dist-info/METADATA
ChromePy-0.0.4.dist-info/WHEEL
ChromePy-0.0.4.dist-info/top_level.txt
ChromePy-0.0.4.dist-info/RECORD
