Metadata-Version: 2.1
Name: ChromePy
Version: 0.0.4
Summary: Python Selenium Remote for ChromeDriver
Home-page: https://github.com/matheusvanzan/chromepy
Author: Matheus Vanzan
Author-email: matheusvnzn@gmail.com
License: UNKNOWN
Platform: UNKNOWN
Classifier: Programming Language :: Python :: 3
Classifier: License :: OSI Approved :: MIT License
Classifier: Operating System :: OS Independent
